{"assets/fonts/Poppins-Bold.ttf":["assets/fonts/Poppins-Bold.ttf"],"assets/fonts/Poppins-Light.ttf":["assets/fonts/Poppins-Light.ttf"],"assets/fonts/Poppins-Medium.ttf":["assets/fonts/Poppins-Medium.ttf"],"assets/fonts/Poppins-Regular.ttf":["assets/fonts/Poppins-Regular.ttf"],"assets/fonts/Poppins-Thin.ttf":["assets/fonts/Poppins-Thin.ttf"],"assets/images/design.png":["assets/images/design.png"],"assets/images/figmalogo.png":["assets/images/figmalogo.png"],"assets/images/flutterlogo.png":["assets/images/flutterlogo.png"],"assets/images/getsite.png":["assets/images/getsite.png"],"assets/images/git.png":["assets/images/git.png"],"assets/images/ig.png":["assets/images/ig.png"],"assets/images/in.png":["assets/images/in.png"],"assets/images/logotarsis.png":["assets/images/logotarsis.png"],"assets/images/maya.png":["assets/images/maya.png"],"assets/images/mayalogo.png":["assets/images/mayalogo.png"],"assets/images/pedro.png":["assets/images/pedro.png"],"assets/images/pedrosite.png":["assets/images/pedrosite.png"],"assets/images/robo1.png":["assets/images/robo1.png"],"assets/images/robo2.png":["assets/images/robo2.png"],"assets/images/tarsis.jpg":["assets/images/tarsis.jpg"],"assets/images/unity.png":["assets/images/unity.png"],"assets/images/unitylogo.png":["assets/images/unitylogo.png"],"assets/images/vamossite.png":["assets/images/vamossite.png"],"assets/images/web.png":["assets/images/web.png"],"packages/cupertino_icons/assets/CupertinoIcons.ttf":["packages/cupertino_icons/assets/CupertinoIcons.ttf"],"packages/social_media_buttons/fonts/SocialMediaIcons.ttf":["packages/social_media_buttons/fonts/SocialMediaIcons.ttf"]}